fitbit_client
