Metadata-Version: 2.1
Name: fitbit-client
Version: 0.0.2
Summary: Call Fitbit's web API from terminal
Home-page: https://github.com/robotpt/fitbit-client
Author: Audrow Nash
Author-email: audrow.nash@gmail.com
License: MIT
Platform: UNKNOWN
Classifier: License :: OSI Approved :: MIT License
Classifier: Programming Language :: Python
Classifier: Programming Language :: Python :: 3
Classifier: Programming Language :: Python :: 3.6
Classifier: Programming Language :: Python :: Implementation :: CPython
Classifier: Programming Language :: Python :: Implementation :: PyPy
Requires-Python: >=3.6.0
